{
  "apartment": "Via della Scala",
  "languages": ["it", "en", "fr", "de", "es"],
  "intents": {
    "it": {
      "heating": ["riscaldamento", "termosifoni", "caldo", "freddo", "accendere"],
      "trash": ["spazzatura", "rifiuti", "immondizia", "buttare"],
      "electric_panel": ["quadro elettrico", "salta la luce", "corrente", "elettricità"],
      "wifi": ["wifi", "internet", "rete", "password"],
      "check_in": ["check in", "arrivo", "citofono", "entrare"],
      "early_checkin_policy": ["early check in", "check in anticipato", "arrivare prima"],
      "check_out": ["check out", "partenza", "lasciare"],
      "linens_towels": ["asciugamani", "lenzuola", "biancheria", "cambio"],
      "water": ["acqua", "acqua calda", "potabile"],
      "bathroom": ["bagno", "doccia", "wc", "carta igienica"],
      "AC": ["aria condizionata", "condizionatore", "telecomando"],
      "gas": ["gas", "fornelli", "cucinare"],
      "eat": ["mangiare", "ristoranti", "cena", "pranzo"],
      "drink": ["bere", "bar", "vino", "cocktail"],
      "shopping": ["shopping", "negozi", "mercato"],
      "visit": ["visitare", "cosa vedere", "monumenti"],
      "experiences": ["esperienze", "romantico", "tour"],
      "day_trips": ["gite", "escursioni", "fuori roma"],
      "tickets": ["biglietti", "concerti", "partite"],
      "museums": ["musei", "vaticano", "colosseo"],
      "exhibitions": ["mostre", "esposizioni"],
      "transport": ["trasporti", "bus", "tram", "metro"],
      "services": ["servizi", "farmacia", "ospedale", "atm"],
      "emergency": ["emergenza", "polizia", "ambulanza"],
      "house_rules": ["regole", "rumore", "fumo", "feste"],
      "laundry": ["lavanderia", "lavatrice"],
      "wifi_troubleshooting": ["wifi non funziona", "problema internet"],
      "late_checkout_policy": ["late check out", "partenza tardiva"],
      "luggage_storage": ["bagagli", "valigie", "deposito"],
      "id_documents": ["documenti", "passaporto", "carta identità"],
      "payment_methods": ["pagamento", "pagare", "carta di credito"],
      "city_tax_info": ["tassa soggiorno", "tassa turistica"],
      "city_tax_payment_issue": ["problema tassa", "errore pagamento"],
      "receipt_rental": ["ricevuta soggiorno", "fattura"],
      "receipt_city_tax": ["ricevuta tassa"]
    },
    "en": {
      "heating": ["heating", "radiators", "warm", "cold", "turn on"],
      "trash": ["trash", "garbage", "rubbish", "recycling", "waste"],
      "electric_panel": ["electric panel", "power cut", "electricity", "blackout", "no light"],
      "wifi": ["wifi", "internet", "network", "password"],
      "check_in": ["check in", "arrival", "intercom", "doorbell", "how to enter"],
      "early_checkin_policy": ["early check in", "arrive early", "earlier"],
      "check_out": ["check out", "leave", "leaving", "departure"],
      "linens_towels": ["towels", "linens", "sheets", "blankets"],
      "water": ["water", "hot water", "tap water", "drinkable"],
      "bathroom": ["bathroom", "shower", "toilet", "toilet paper"],
      "AC": ["air conditioning", "ac", "cool", "remote control"],
      "gas": ["gas", "stove", "cooker", "kitchen"],
      "eat": ["eat", "restaurants", "dinner", "lunch", "food"],
      "drink": ["drink", "bar", "wine", "cocktail", "pubs"],
      "shopping": ["shopping", "market", "stores", "supermarket"],
      "visit": ["visit", "see", "monuments", "walking"],
      "experiences": ["experiences", "tours", "activities"],
      "day_trips": ["day trips", "excursions", "outside rome"],
      "tickets": ["tickets", "events", "concerts"],
      "museums": ["museums", "vatican", "colosseum"],
      "exhibitions": ["exhibitions", "shows", "art"],
      "transport": ["transport", "bus", "tram", "train", "taxi"],
      "services": ["services", "pharmacy", "atm", "hospital", "bank"],
      "emergency": ["emergency", "police", "help", "ambulance"],
      "house_rules": ["house rules", "smoking", "parties", "noise"],
      "laundry": ["laundry", "wash", "washing machine"],
      "wifi_troubleshooting": ["wifi not working", "no internet", "slow wifi"],
      "late_checkout_policy": ["late check out", "stay longer"],
      "luggage_storage": ["luggage", "bags", "suitcases", "storage"],
      "id_documents": ["documents", "passport", "id card"],
      "payment_methods": ["payment", "pay", "credit card"],
      "city_tax_info": ["city tax", "tourist tax"],
      "city_tax_payment_issue": ["city tax problem", "tax link", "payment error"],
      "receipt_rental": ["rental receipt", "invoice", "bill"],
      "receipt_city_tax": ["city tax receipt"]
    },
    "es": {
      "heating": ["calefacción", "radiadores", "calor", "encender"],
      "trash": ["basura", "residuos", "reciclaje"],
      "electric_panel": ["cuadro electrico", "luz", "corriente", "electricidad"],
      "wifi": ["wifi", "internet", "red", "contraseña"],
      "check_in": ["check in", "llegada", "portero", "entrar"],
      "early_checkin_policy": ["early check in", "entrada anticipada", "llegar antes"],
      "check_out": ["check out", "salida", "dejar"],
      "linens_towels": ["toallas", "sabanas", "ropa de cama"],
      "water": ["agua", "agua caliente", "bebible"],
      "bathroom": ["baño", "ducha", "wc", "papel higienico"],
      "AC": ["aire acondicionado", "mando"],
      "gas": ["gas", "cocina", "fuego"],
      "eat": ["comer", "restaurantes", "cena", "almuerzo"],
      "drink": ["beber", "bar", "vino", "copas"],
      "shopping": ["compras", "tiendas", "mercado"],
      "visit": ["visitar", "que ver", "monumentos"],
      "experiences": ["experiencias", "tours"],
      "day_trips": ["excursiones", "fuera de roma"],
      "tickets": ["entradas", "tickets"],
      "museums": ["museos", "vaticano", "coliseo"],
      "exhibitions": ["exposiciones", "arte"],
      "transport": ["transporte", "autobus", "metro"],
      "services": ["servicios", "farmacia", "cajero"],
      "emergency": ["emergencia", "policia", "ayuda"],
      "house_rules": ["normas", "reglas", "humo", "fiestas"],
      "laundry": ["lavanderia", "lavadora"],
      "wifi_troubleshooting": ["wifi no funciona", "sin internet"],
      "late_checkout_policy": ["late check out", "salida tardia"],
      "luggage_storage": ["equipaje", "maletas", "consigna"],
      "id_documents": ["documentos", "pasaporte", "dni"],
      "payment_methods": ["pago", "pagar", "tarjeta"],
      "city_tax_info": ["tasa turistica", "tasa estancia"],
      "city_tax_payment_issue": ["problema tasa", "error pago"],
      "receipt_rental": ["recibo", "factura"],
      "receipt_city_tax": ["recibo tasa"]
    }
  },
  "answers": {
    "it": {
      "heating": "Riscaldamento: Per accenderlo vai in camera da letto. Guardando la finestra, sulla sinistra (di fronte al letto) trovi un piccolo termostato: metti l’interruttore in alto su ON e imposta la ghiera a 26 °C. Dopo pochi minuti i termosifoni inizieranno a scaldarsi.",
      "trash": "Spazzatura: Prima di lasciare l’appartamento, butta i rifiuti negli appositi cestini. Facciamo raccolta differenziata (WeDoRecycling): porta i sacchetti a fine Via della Scala, angolo Via Garibaldi, tutti i giorni dalle 8:00 alle 9:30.",
      "electric_panel": "Quadro elettrico: Se salta la corrente, uscendo dall’appartamento (guardando la porta) il quadro è sulla destra: controlla che tutti gli interruttori siano verso l’alto. Se la corrente non torna, sopra il quadro c’è uno sportello in legno: premi per aprirlo e rialza anche l’interruttore generale che trovi dietro.",
      "wifi": "Wi-Fi: Il router è sul lato destro del soggiorno, appoggiato su una panca. SSID e password sono indicati sull’etichetta del router.",
      "check_in": "Check-in dalle 15:00. Citofono esterno: colonna sinistra, primo pulsante dal basso. Citofono interno: A/1.",
      "early_checkin_policy": "Early check-in: Il check-in standard è dalle 15:00. Se vuoi arrivare prima, scrivimi l’orario esatto. Se l’appartamento è già pronto possiamo anticipare, ma NON è garantito.",
      "check_out": "Prima di partire: spegni le luci, chiudi le finestre e lascia le chiavi sul tavolo. Chiudi la porta e verifica che sia ben chiusa.",
      "linens_towels": "Biancheria e asciugamani: All’arrivo trovi il letto pronto con lenzuola e asciugamani puliti (1 grande + 1 medio per ospite). Il cambio non è giornaliero.",
      "water": "Acqua: L’acqua del rubinetto è potabile. L’acqua calda è sempre disponibile, ma può impiegare qualche minuto ad arrivare.",
      "bathroom": "Bagno: Trovi asciugamani, phon, tappetino, carta igienica e sapone. Non gettare nulla tranne la carta igienica nel WC.",
      "AC": "Aria condizionata: Si gestisce con il telecomando. Ti chiediamo di spegnerla sempre quando esci dall’appartamento.",
      "gas": "Gas: Leva orizzontale = gas aperto; leva verso il basso = gas chiuso. Chiuderlo sempre dopo l'uso.",
      "eat": "Dove mangiare: In zona Trastevere consigliamo Da Teo, La Scala, Da Carlone, Tonnarello, Nannarella.",
      "drink": "Dove bere: Per un bicchiere di vino o un drink: VinAllegro, Freni e Frizioni, Bar San Calisto.",
      "shopping": "Shopping: Mercato di San Cosimato, Antica Norcineria, Valzani, Twice Vintage.",
      "visit": "Cosa visitare: Basilica di Santa Maria in Trastevere, Santa Cecilia, Orto Botanico, Villa Farnesina.",
      "experiences": "Esperienze: Passeggiata panoramica per Trastevere, tramonto a Ponte Sisto.",
      "day_trips": "Gite: Ostia Antica, Tivoli, Castelli Romani.",
      "tickets": "Biglietti: Per concerti e partite usa TicketOne o i canali ufficiali.",
      "museums": "Musei: Musei Vaticani, Colosseo, Galleria Borghese (consigliata la prenotazione).",
      "exhibitions": "Mostre: Controlla il MAXXI, il Palazzo delle Esposizioni e le Scuderie del Quirinale.",
      "transport": "Trasporti: Tram 8 verso Piazza Venezia; bus 23 e H verso il centro e Termini.",
      "services": "Servizi: Farmacie a Trastevere, Ospedale Regina Margherita, diversi ATM in zona.",
      "emergency": "Emergenze: 112 Numero di emergenza unico europeo.",
      "house_rules": "Regole: Rispetto del vicinato, no feste, no musica alta dopo le 22:00, vietato fumare.",
      "laundry": "Lavanderia: Se hai bisogno di lavare vestiti, scrivimi per le opzioni in zona.",
      "wifi_troubleshooting": "Wi-Fi non funziona: 1) Controlla router acceso. 2) Riavvia per 30 secondi. 3) Verifica SSID/PWD.",
      "late_checkout_policy": "Late check-out: Il check-out standard è alle 11:00. Su disponibilità è possibile un piccolo ritardo, ma non è automatico.",
      "luggage_storage": "Deposito bagagli: Quando possibile teniamo i bagagli o suggeriamo depositi vicini.",
      "id_documents": "Documenti: La legge richiede la registrazione degli ospiti. Serve un documento valido per tutti.",
      "payment_methods": "Pagamenti: Soggiorno via piattaforma, tassa di soggiorno via link o contanti.",
      "city_tax_info": "Tassa di soggiorno: A Roma è di 5 € a persona a notte.",
      "city_tax_payment_issue": "Problemi tassa: Se il link non funziona, avvisami e sistemo.",
      "receipt_rental": "Ricevuta soggiorno: Possiamo rilasciarla su richiesta.",
      "receipt_city_tax": "Ricevuta tassa: Rilasciamo ricevuta separata per il pagamento della tassa."
    },
    "en": {
      "heating": "Heating: To turn it on, go to the bedroom. Facing the window, on the left (opposite the bed), you will find a small thermostat: set the switch to ON and the dial to 26 °C. After a few minutes, the radiators will start to warm up.",
      "trash": "Trash: Before leaving the apartment, please dispose of the waste in the designated bins. We practice separate waste collection (WeDoRecycling): take the bags to the end of Via della Scala, corner of Via Garibaldi, every day between 8:00 AM and 9:30 AM.",
      "electric_panel": "Electric panel: If the power goes out, as you leave the apartment (looking at the door), the panel is on the right: check that all switches are up. If the power doesn't come back, there is a wooden hatch above the panel: press to open it and reset the main switch found behind it.",
      "wifi": "Wi-Fi: The router is on the right side of the living room, placed on a bench. The SSID and password are on the router's label.",
      "check_in": "Check-in is from 3:00 PM. External intercom: left column, first button from the bottom. Internal intercom: A/1.",
      "early_checkin_policy": "Early check-in: Standard check-in is from 3:00 PM. If you wish to arrive earlier, please let me know your exact time. If the apartment is ready, we can arrange an earlier entry, but it is NOT guaranteed.",
      "check_out": "Before leaving: turn off the lights, close the windows, and leave the keys on the table. Close the door and make sure it is securely locked.",
      "linens_towels": "Linens and towels: Upon arrival, you will find the bed ready with clean sheets and towels (1 large + 1 medium for each guest). Towels are not changed daily.",
      "water": "Water: Tap water is drinkable. Hot water is always available, but especially in the morning, it may take a few minutes to arrive.",
      "bathroom": "Bathroom: You will find towels, a hairdryer, a mat, toilet paper, and soap. Do not flush anything other than toilet paper.",
      "AC": "Air conditioning: Managed via remote control. We kindly ask you to always turn it off when leaving the apartment.",
      "gas": "Gas: Horizontal lever = gas open; downward lever = gas closed. Close it always after use.",
      "eat": "Where to eat: In the Trastevere area, we recommend Da Teo, La Scala, Da Carlone, Tonnarello, Nannarella.",
      "drink": "Where to drink: For a glass of wine or a drink: VinAllegro, Freni e Frizioni, Bar San Calisto.",
      "shopping": "Shopping: San Cosimato Market, Antica Norcineria, Valzani, Twice Vintage.",
      "visit": "What to visit: Basilica of Santa Maria in Trastevere, Santa Cecilia, Botanical Garden, Villa Farnesina.",
      "experiences": "Experiences: Panoramic walk through Trastevere, sunset at Ponte Sisto.",
      "day_trips": "Day trips: Ostia Antica, Tivoli, Castelli Romani.",
      "tickets": "Event tickets: Use TicketOne and official channels for concerts or matches.",
      "museums": "Main museums: Vatican Museums, Colosseum, Borghese Gallery (reservation recommended).",
      "exhibitions": "Exhibitions: Check MAXXI, Palazzo delle Esposizioni, and Scuderie del Quirinale.",
      "transport": "Transport: Tram 8 towards Piazza Venezia; buses 23 and H towards the center and Termini.",
      "services": "Local services: Pharmacies in Trastevere, Regina Margherita Hospital, several ATMs in the area.",
      "emergency": "Emergencies: 112 EU Emergency number.",
      "house_rules": "House rules: Please respect the neighbors, no parties, no loud music after 10:00 PM, no smoking.",
      "laundry": "Laundry: If you need to wash clothes, message me for the best options in Trastevere.",
      "wifi_troubleshooting": "Wi-Fi troubleshooting: 1) Check if the router is on. 2) Unplug it for 30 seconds and plug it back in. 3) Verify network name and password.",
      "late_checkout_policy": "Late check-out: Standard check-out is at 11:00 AM. A slight extension may be possible based on availability, but it is not automatic.",
      "luggage_storage": "Luggage storage: When possible, we can hold bags after check-out or suggest a nearby storage service.",
      "id_documents": "ID Documents: Italian law requires guest registration. A valid ID is needed for everyone.",
      "payment_methods": "Payments: The stay is paid through the platform. The city tax is paid separately via link or cash.",
      "city_tax_info": "City tax: In Rome, it is 5 € per person per night.",
      "city_tax_payment_issue": "City tax payment issues: If the link doesn't work, let me know and I will fix it.",
      "receipt_rental": "Stay receipt: We can provide a receipt upon request.",
      "receipt_city_tax": "City tax receipt: A separate receipt can be provided for the city tax payment."
    },
    "es": {
      "heating": "Calefacción: Para encenderla vaya al dormitorio. A la izquierda de la cama hay un pequeño termostato: ponga el interruptor en ON y ajuste a 26 °C.",
      "trash": "Basura: Tire los residuos en los contenedores adecuados al final de Via della Scala, esquina Via Garibaldi, todos los días de 8:00 a 9:30.",
      "electric_panel": "Cuadro eléctrico: Al salir del apartamento, el cuadro está a la derecha. Si no vuelve la luz, suba el interruptor general tras la tapa de madera.",
      "wifi": "Wi-Fi: El router está a la derecha del salón sobre un banco. SSID y contraseña en la etiqueta del router.",
      "check_in": "Check-in desde las 15:00. Portero exterior: columna izquierda, botón inferior. Portero interior: A/1.",
      "early_checkin_policy": "Check-in temprano: No garantizado. Escríbame su horario de llegada para consultar disponibilidad.",
      "check_out": "Salida: Apague luces, cierre ventanas y deje las llaves en la mesa. Verifique que la puerta esté bien cerrada.",
      "linens_towels": "Ropa de cama y toallas: Cama preparada a la llegada con toallas limpias. No hay cambio diario.",
      "water": "Agua: El agua del grifo es potable. El agua caliente puede tardar unos minutos por la mañana.",
      "bathroom": "Baño: Toallas, secador, papel higiénico y jabón disponibles. No tire nada excepto papel al inodoro.",
      "AC": "Aire acondicionado: Se maneja con el mando. Por favor, apáguelo siempre al salir.",
      "gas": "Gas: Palanca horizontal = abierto; hacia abajo = cerrado. Cerrar siempre tras usar.",
      "eat": "Dónde comer: Recomendados: Da Teo, La Scala, Da Carlone, Tonnarello, Nannarella.",
      "drink": "Dónde beber: VinAllegro, Freni e Frizioni, Bar San Calisto.",
      "shopping": "Compras: Mercado San Cosimato, Antica Norcineria, Valzani, Twice Vintage.",
      "visit": "Qué visitar: Santa Maria in Trastevere, Santa Cecilia, Orto Botanico, Villa Farnesina.",
      "experiences": "Experiencias: Paseo por Trastevere, atardecer en Ponte Sisto.",
      "day_trips": "Excursiones: Ostia Antica, Tivoli, Castelli Romani.",
      "tickets": "Entradas: TicketOne para conciertos y partidos.",
      "museums": "Museos: Museos Vaticanos, Coliseo, Galería Borghese.",
      "exhibitions": "Exposiciones: MAXXI, Palazzo delle Esposizioni, Scuderie del Quirinale.",
      "transport": "Transporte: Tranvía 8 hacia Piazza Venezia; buses 23 y H.",
      "services": "Servicios: Farmacias, hospital Regina Margherita, cajeros en la zona.",
      "emergency": "Emergencias: 112 número de emergencia europeo.",
      "house_rules": "Normas: Respete el vecindario, sin fiestas, silencio tras las 22:00, no fumar.",
      "laundry": "Lavandería: Escríbame para conocer las mejores opciones en Trastevere.",
      "wifi_troubleshooting": "Wi-Fi no funciona: 1) Revise si está encendido. 2) Reinicie 30 segundos. 3) Verifique SSID/PWD.",
      "late_checkout_policy": "Salida tardía: Sujeta a disponibilidad, no es automática.",
      "luggage_storage": "Equipaje: Según disponibilidad, podemos guardarlo o sugerir consignas.",
      "id_documents": "Documentos: La ley italiana exige el registro de huéspedes con un documento válido.",
      "payment_methods": "Pagos: Estancia por plataforma, tasa turística por link o en efectivo.",
      "city_tax_info": "Tasa turística: En Roma es de 5 € por persona y noche.",
      "city_tax_payment_issue": "Problemas tasa: Si el link no funciona, avíseme para solucionarlo.",
      "receipt_rental": "Recibo: Disponible bajo solicitud.",
      "receipt_city_tax": "Recibo tasa: Se entrega recibo separado por el pago de la tasa."
    }
  }
}
